quart_shell_ipython.py
quart_shell_ipython-0.1.2.dist-info/METADATA
quart_shell_ipython-0.1.2.dist-info/WHEEL
quart_shell_ipython-0.1.2.dist-info/entry_points.txt
quart_shell_ipython-0.1.2.dist-info/licenses/LICENSE
quart_shell_ipython-0.1.2.dist-info/RECORD
