Metadata-Version: 2.4
Name: quart-shell-ipython
Version: 0.1.2
Summary: Startup the quart shell with ipython
License: MIT
License-File: LICENSE
Author: hs
Author-email: huangxiaohen2738@gmail.com
Requires-Python: >=3.7
Classifier: Environment :: Web Environment
Classifier: Intended Audience :: Developers
Classifier: License :: OSI Approved :: MIT License
Classifier: Programming Language :: Python
Classifier: Programming Language :: Python :: 3
Classifier: Programming Language :: Python :: 3.7
Classifier: Programming Language :: Python :: 3.8
Classifier: Programming Language :: Python :: 3.9
Classifier: Programming Language :: Python :: 3.10
Classifier: Programming Language :: Python :: 3.11
Classifier: Programming Language :: Python :: 3.12
Classifier: Programming Language :: Python :: 3.13
Classifier: Programming Language :: Python :: 3.14
Requires-Dist: ipython
Requires-Dist: quart
Project-URL: Repository, https://github.com/ponytailer/quart-shell-ipython.git
